{
    "Items": [
        {
            "lastFour": {
                "S": "0069"
            },
            "valid": {
                "BOOL": false
            },
            "expMonth": {
                "N": "2"
            },
            "emailAddress": {
                "S": "stuheadz@gmail.com"
            },
            "expYear": {
                "N": "2043"
            },
            "paymentMethodId": {
                "S": "pm_1IiAcVKsNNk3qPPURqWZTtoJ"
            },
            "paymentMethodObj": {
                "M": {
                    "billing_details": {
                        "M": {
                            "name": {
                                "NULL": true
                            },
                            "address": {
                                "M": {
                                    "country": {
                                        "NULL": true
                                    },
                                    "state": {
                                        "NULL": true
                                    },
                                    "postal_code": {
                                        "S": "34343"
                                    },
                                    "city": {
                                        "NULL": true
                                    },
                                    "line2": {
                                        "NULL": true
                                    },
                                    "line1": {
                                        "NULL": true
                                    }
                                }
                            },
                            "phone": {
                                "NULL": true
                            },
                            "email": {
                                "NULL": true
                            }
                        }
                    },
                    "livemode": {
                        "BOOL": false
                    },
                    "created": {
                        "N": "1618890687"
                    },
                    "id": {
                        "S": "pm_1IiAcVKsNNk3qPPURqWZTtoJ"
                    },
                    "type": {
                        "S": "card"
                    },
                    "card": {
                        "M": {
                            "country": {
                                "S": "US"
                            },
                            "last4": {
                                "S": "0069"
                            },
                            "funding": {
                                "S": "credit"
                            },
                            "checks": {
                                "M": {
                                    "address_postal_code_check": {
                                        "NULL": true
                                    },
                                    "address_line1_check": {
                                        "NULL": true
                                    },
                                    "cvc_check": {
                                        "NULL": true
                                    }
                                }
                            },
                            "three_d_secure_usage": {
                                "M": {
                                    "supported": {
                                        "BOOL": true
                                    }
                                }
                            },
                            "wallet": {
                                "NULL": true
                            },
                            "generated_from": {
                                "NULL": true
                            },
                            "exp_month": {
                                "N": "2"
                            },
                            "exp_year": {
                                "N": "2043"
                            },
                            "networks": {
                                "M": {
                                    "available": {
                                        "L": [
                                            {
                                                "S": "visa"
                                            }
                                        ]
                                    },
                                    "preferred": {
                                        "NULL": true
                                    }
                                }
                            },
                            "brand": {
                                "S": "visa"
                            }
                        }
                    },
                    "object": {
                        "S": "payment_method"
                    },
                    "customer": {
                        "NULL": true
                    }
                }
            },
            "active": {
                "BOOL": false
            },
            "savedAt": {
                "N": "1618890615182"
            },
            "ID": {
                "S": "6adddcaf-90b1-40e8-a1ec-79154f60a8fc"
            },
            "userId": {
                "S": "cb7650ca-214a-43df-a23d-27e8d7e585e0"
            },
            "brand": {
                "S": "visa"
            }
        },
        {
            "lastFour": {
                "S": "0341"
            },
            "valid": {
                "BOOL": false
            },
            "expMonth": {
                "N": "4"
            },
            "emailAddress": {
                "S": "stuheadz@gmail.com"
            },
            "expYear": {
                "N": "2023"
            },
            "paymentMethodId": {
                "S": "pm_1IiAaQKsNNk3qPPU3oimCgYx"
            },
            "paymentMethodObj": {
                "M": {
                    "billing_details": {
                        "M": {
                            "name": {
                                "NULL": true
                            },
                            "address": {
                                "M": {
                                    "country": {
                                        "NULL": true
                                    },
                                    "state": {
                                        "NULL": true
                                    },
                                    "postal_code": {
                                        "S": "23423"
                                    },
                                    "city": {
                                        "NULL": true
                                    },
                                    "line2": {
                                        "NULL": true
                                    },
                                    "line1": {
                                        "NULL": true
                                    }
                                }
                            },
                            "phone": {
                                "NULL": true
                            },
                            "email": {
                                "NULL": true
                            }
                        }
                    },
                    "livemode": {
                        "BOOL": false
                    },
                    "created": {
                        "N": "1618890559"
                    },
                    "id": {
                        "S": "pm_1IiAaQKsNNk3qPPU3oimCgYx"
                    },
                    "type": {
                        "S": "card"
                    },
                    "card": {
                        "M": {
                            "country": {
                                "S": "US"
                            },
                            "last4": {
                                "S": "0341"
                            },
                            "funding": {
                                "S": "credit"
                            },
                            "checks": {
                                "M": {
                                    "address_postal_code_check": {
                                        "NULL": true
                                    },
                                    "address_line1_check": {
                                        "NULL": true
                                    },
                                    "cvc_check": {
                                        "NULL": true
                                    }
                                }
                            },
                            "three_d_secure_usage": {
                                "M": {
                                    "supported": {
                                        "BOOL": true
                                    }
                                }
                            },
                            "wallet": {
                                "NULL": true
                            },
                            "generated_from": {
                                "NULL": true
                            },
                            "exp_month": {
                                "N": "4"
                            },
                            "exp_year": {
                                "N": "2023"
                            },
                            "networks": {
                                "M": {
                                    "available": {
                                        "L": [
                                            {
                                                "S": "visa"
                                            }
                                        ]
                                    },
                                    "preferred": {
                                        "NULL": true
                                    }
                                }
                            },
                            "brand": {
                                "S": "visa"
                            }
                        }
                    },
                    "object": {
                        "S": "payment_method"
                    },
                    "customer": {
                        "NULL": true
                    }
                }
            },
            "active": {
                "BOOL": false
            },
            "savedAt": {
                "N": "1618890486612"
            },
            "ID": {
                "S": "a3c73f32-2720-4a8f-8185-05d92e43e581"
            },
            "userId": {
                "S": "cb7650ca-214a-43df-a23d-27e8d7e585e0"
            },
            "brand": {
                "S": "visa"
            }
        },
        {
            "lastFour": {
                "S": "4954"
            },
            "valid": {
                "BOOL": false
            },
            "expMonth": {
                "N": "2"
            },
            "emailAddress": {
                "S": "stuheadz@gmail.com"
            },
            "expYear": {
                "N": "2032"
            },
            "paymentMethodId": {
                "S": "pm_1IiAaiKsNNk3qPPUvzq8NqFw"
            },
            "paymentMethodObj": {
                "M": {
                    "billing_details": {
                        "M": {
                            "name": {
                                "NULL": true
                            },
                            "address": {
                                "M": {
                                    "country": {
                                        "NULL": true
                                    },
                                    "state": {
                                        "NULL": true
                                    },
                                    "postal_code": {
                                        "S": "23232"
                                    },
                                    "city": {
                                        "NULL": true
                                    },
                                    "line2": {
                                        "NULL": true
                                    },
                                    "line1": {
                                        "NULL": true
                                    }
                                }
                            },
                            "phone": {
                                "NULL": true
                            },
                            "email": {
                                "NULL": true
                            }
                        }
                    },
                    "livemode": {
                        "BOOL": false
                    },
                    "created": {
                        "N": "1618890576"
                    },
                    "id": {
                        "S": "pm_1IiAaiKsNNk3qPPUvzq8NqFw"
                    },
                    "type": {
                        "S": "card"
                    },
                    "card": {
                        "M": {
                            "country": {
                                "S": "US"
                            },
                            "last4": {
                                "S": "4954"
                            },
                            "funding": {
                                "S": "credit"
                            },
                            "checks": {
                                "M": {
                                    "address_postal_code_check": {
                                        "NULL": true
                                    },
                                    "address_line1_check": {
                                        "NULL": true
                                    },
                                    "cvc_check": {
                                        "NULL": true
                                    }
                                }
                            },
                            "three_d_secure_usage": {
                                "M": {
                                    "supported": {
                                        "BOOL": true
                                    }
                                }
                            },
                            "wallet": {
                                "NULL": true
                            },
                            "generated_from": {
                                "NULL": true
                            },
                            "exp_month": {
                                "N": "2"
                            },
                            "exp_year": {
                                "N": "2032"
                            },
                            "networks": {
                                "M": {
                                    "available": {
                                        "L": [
                                            {
                                                "S": "visa"
                                            }
                                        ]
                                    },
                                    "preferred": {
                                        "NULL": true
                                    }
                                }
                            },
                            "brand": {
                                "S": "visa"
                            }
                        }
                    },
                    "object": {
                        "S": "payment_method"
                    },
                    "customer": {
                        "NULL": true
                    }
                }
            },
            "active": {
                "BOOL": false
            },
            "savedAt": {
                "N": "1618890503912"
            },
            "ID": {
                "S": "d4504a29-182c-43d6-9762-184d0b532665"
            },
            "userId": {
                "S": "cb7650ca-214a-43df-a23d-27e8d7e585e0"
            },
            "brand": {
                "S": "visa"
            }
        },
        {
            "lastFour": {
                "S": "9995"
            },
            "valid": {
                "BOOL": false
            },
            "expMonth": {
                "N": "3"
            },
            "emailAddress": {
                "S": "stuheadz@gmail.com"
            },
            "expYear": {
                "N": "2043"
            },
            "paymentMethodId": {
                "S": "pm_1IiAbVKsNNk3qPPUNvXsZGIc"
            },
            "paymentMethodObj": {
                "M": {
                    "billing_details": {
                        "M": {
                            "name": {
                                "NULL": true
                            },
                            "address": {
                                "M": {
                                    "country": {
                                        "NULL": true
                                    },
                                    "state": {
                                        "NULL": true
                                    },
                                    "postal_code": {
                                        "S": "34343"
                                    },
                                    "city": {
                                        "NULL": true
                                    },
                                    "line2": {
                                        "NULL": true
                                    },
                                    "line1": {
                                        "NULL": true
                                    }
                                }
                            },
                            "phone": {
                                "NULL": true
                            },
                            "email": {
                                "NULL": true
                            }
                        }
                    },
                    "livemode": {
                        "BOOL": false
                    },
                    "created": {
                        "N": "1618890625"
                    },
                    "id": {
                        "S": "pm_1IiAbVKsNNk3qPPUNvXsZGIc"
                    },
                    "type": {
                        "S": "card"
                    },
                    "card": {
                        "M": {
                            "country": {
                                "S": "US"
                            },
                            "last4": {
                                "S": "9995"
                            },
                            "funding": {
                                "S": "credit"
                            },
                            "checks": {
                                "M": {
                                    "address_postal_code_check": {
                                        "NULL": true
                                    },
                                    "address_line1_check": {
                                        "NULL": true
                                    },
                                    "cvc_check": {
                                        "NULL": true
                                    }
                                }
                            },
                            "three_d_secure_usage": {
                                "M": {
                                    "supported": {
                                        "BOOL": true
                                    }
                                }
                            },
                            "wallet": {
                                "NULL": true
                            },
                            "generated_from": {
                                "NULL": true
                            },
                            "exp_month": {
                                "N": "3"
                            },
                            "exp_year": {
                                "N": "2043"
                            },
                            "networks": {
                                "M": {
                                    "available": {
                                        "L": [
                                            {
                                                "S": "visa"
                                            }
                                        ]
                                    },
                                    "preferred": {
                                        "NULL": true
                                    }
                                }
                            },
                            "brand": {
                                "S": "visa"
                            }
                        }
                    },
                    "object": {
                        "S": "payment_method"
                    },
                    "customer": {
                        "NULL": true
                    }
                }
            },
            "active": {
                "BOOL": false
            },
            "savedAt": {
                "N": "1618890553277"
            },
            "ID": {
                "S": "cf8d5af0-41ed-40f2-a3f8-c9bef27d1911"
            },
            "userId": {
                "S": "cb7650ca-214a-43df-a23d-27e8d7e585e0"
            },
            "brand": {
                "S": "visa"
            }
        },
        {
            "lastFour": {
                "S": "0127"
            },
            "valid": {
                "BOOL": false
            },
            "expMonth": {
                "N": "2"
            },
            "emailAddress": {
                "S": "stuheadz@gmail.com"
            },
            "expYear": {
                "N": "2032"
            },
            "paymentMethodId": {
                "S": "pm_1IiAd0KsNNk3qPPUs9ZydVdt"
            },
            "paymentMethodObj": {
                "M": {
                    "billing_details": {
                        "M": {
                            "name": {
                                "NULL": true
                            },
                            "address": {
                                "M": {
                                    "country": {
                                        "NULL": true
                                    },
                                    "state": {
                                        "NULL": true
                                    },
                                    "postal_code": {
                                        "S": "23232"
                                    },
                                    "city": {
                                        "NULL": true
                                    },
                                    "line2": {
                                        "NULL": true
                                    },
                                    "line1": {
                                        "NULL": true
                                    }
                                }
                            },
                            "phone": {
                                "NULL": true
                            },
                            "email": {
                                "NULL": true
                            }
                        }
                    },
                    "livemode": {
                        "BOOL": false
                    },
                    "created": {
                        "N": "1618890718"
                    },
                    "id": {
                        "S": "pm_1IiAd0KsNNk3qPPUs9ZydVdt"
                    },
                    "type": {
                        "S": "card"
                    },
                    "card": {
                        "M": {
                            "country": {
                                "S": "US"
                            },
                            "last4": {
                                "S": "0127"
                            },
                            "funding": {
                                "S": "credit"
                            },
                            "checks": {
                                "M": {
                                    "address_postal_code_check": {
                                        "NULL": true
                                    },
                                    "address_line1_check": {
                                        "NULL": true
                                    },
                                    "cvc_check": {
                                        "NULL": true
                                    }
                                }
                            },
                            "three_d_secure_usage": {
                                "M": {
                                    "supported": {
                                        "BOOL": true
                                    }
                                }
                            },
                            "wallet": {
                                "NULL": true
                            },
                            "generated_from": {
                                "NULL": true
                            },
                            "exp_month": {
                                "N": "2"
                            },
                            "exp_year": {
                                "N": "2032"
                            },
                            "networks": {
                                "M": {
                                    "available": {
                                        "L": [
                                            {
                                                "S": "visa"
                                            }
                                        ]
                                    },
                                    "preferred": {
                                        "NULL": true
                                    }
                                }
                            },
                            "brand": {
                                "S": "visa"
                            }
                        }
                    },
                    "object": {
                        "S": "payment_method"
                    },
                    "customer": {
                        "NULL": true
                    }
                }
            },
            "active": {
                "BOOL": false
            },
            "savedAt": {
                "N": "1618890646021"
            },
            "ID": {
                "S": "85336241-386b-4592-9677-6f89f931bec4"
            },
            "userId": {
                "S": "cb7650ca-214a-43df-a23d-27e8d7e585e0"
            },
            "brand": {
                "S": "visa"
            }
        },
        {
            "lastFour": {
                "S": "4242"
            },
            "valid": {
                "BOOL": false
            },
            "expMonth": {
                "N": "4"
            },
            "emailAddress": {
                "S": "stuheadz@gmail.com"
            },
            "expYear": {
                "N": "2022"
            },
            "paymentMethodId": {
                "S": "pm_1IiAYxKsNNk3qPPUmFE41RFE"
            },
            "paymentMethodObj": {
                "M": {
                    "billing_details": {
                        "M": {
                            "name": {
                                "NULL": true
                            },
                            "address": {
                                "M": {
                                    "country": {
                                        "NULL": true
                                    },
                                    "state": {
                                        "NULL": true
                                    },
                                    "postal_code": {
                                        "S": "42442"
                                    },
                                    "city": {
                                        "NULL": true
                                    },
                                    "line2": {
                                        "NULL": true
                                    },
                                    "line1": {
                                        "NULL": true
                                    }
                                }
                            },
                            "phone": {
                                "NULL": true
                            },
                            "email": {
                                "NULL": true
                            }
                        }
                    },
                    "livemode": {
                        "BOOL": false
                    },
                    "created": {
                        "N": "1618890467"
                    },
                    "id": {
                        "S": "pm_1IiAYxKsNNk3qPPUmFE41RFE"
                    },
                    "type": {
                        "S": "card"
                    },
                    "card": {
                        "M": {
                            "country": {
                                "S": "US"
                            },
                            "last4": {
                                "S": "4242"
                            },
                            "funding": {
                                "S": "credit"
                            },
                            "checks": {
                                "M": {
                                    "address_postal_code_check": {
                                        "NULL": true
                                    },
                                    "address_line1_check": {
                                        "NULL": true
                                    },
                                    "cvc_check": {
                                        "NULL": true
                                    }
                                }
                            },
                            "three_d_secure_usage": {
                                "M": {
                                    "supported": {
                                        "BOOL": true
                                    }
                                }
                            },
                            "wallet": {
                                "NULL": true
                            },
                            "generated_from": {
                                "NULL": true
                            },
                            "exp_month": {
                                "N": "4"
                            },
                            "exp_year": {
                                "N": "2022"
                            },
                            "networks": {
                                "M": {
                                    "available": {
                                        "L": [
                                            {
                                                "S": "visa"
                                            }
                                        ]
                                    },
                                    "preferred": {
                                        "NULL": true
                                    }
                                }
                            },
                            "brand": {
                                "S": "visa"
                            }
                        }
                    },
                    "object": {
                        "S": "payment_method"
                    },
                    "customer": {
                        "NULL": true
                    }
                }
            },
            "active": {
                "BOOL": false
            },
            "savedAt": {
                "N": "1618890394560"
            },
            "ID": {
                "S": "b7046eb1-efb0-4298-a186-00e24dd42d63"
            },
            "userId": {
                "S": "cb7650ca-214a-43df-a23d-27e8d7e585e0"
            },
            "brand": {
                "S": "visa"
            }
        },
        {
            "lastFour": {
                "S": "9987"
            },
            "valid": {
                "BOOL": false
            },
            "expMonth": {
                "N": "3"
            },
            "emailAddress": {
                "S": "stuheadz@gmail.com"
            },
            "expYear": {
                "N": "2043"
            },
            "paymentMethodId": {
                "S": "pm_1IiAboKsNNk3qPPUCvAtYPrW"
            },
            "paymentMethodObj": {
                "M": {
                    "billing_details": {
                        "M": {
                            "name": {
                                "NULL": true
                            },
                            "address": {
                                "M": {
                                    "country": {
                                        "NULL": true
                                    },
                                    "state": {
                                        "NULL": true
                                    },
                                    "postal_code": {
                                        "S": "34343"
                                    },
                                    "city": {
                                        "NULL": true
                                    },
                                    "line2": {
                                        "NULL": true
                                    },
                                    "line1": {
                                        "NULL": true
                                    }
                                }
                            },
                            "phone": {
                                "NULL": true
                            },
                            "email": {
                                "NULL": true
                            }
                        }
                    },
                    "livemode": {
                        "BOOL": false
                    },
                    "created": {
                        "N": "1618890644"
                    },
                    "id": {
                        "S": "pm_1IiAboKsNNk3qPPUCvAtYPrW"
                    },
                    "type": {
                        "S": "card"
                    },
                    "card": {
                        "M": {
                            "country": {
                                "S": "US"
                            },
                            "last4": {
                                "S": "9987"
                            },
                            "funding": {
                                "S": "credit"
                            },
                            "checks": {
                                "M": {
                                    "address_postal_code_check": {
                                        "NULL": true
                                    },
                                    "address_line1_check": {
                                        "NULL": true
                                    },
                                    "cvc_check": {
                                        "NULL": true
                                    }
                                }
                            },
                            "three_d_secure_usage": {
                                "M": {
                                    "supported": {
                                        "BOOL": true
                                    }
                                }
                            },
                            "wallet": {
                                "NULL": true
                            },
                            "generated_from": {
                                "NULL": true
                            },
                            "exp_month": {
                                "N": "3"
                            },
                            "exp_year": {
                                "N": "2043"
                            },
                            "networks": {
                                "M": {
                                    "available": {
                                        "L": [
                                            {
                                                "S": "visa"
                                            }
                                        ]
                                    },
                                    "preferred": {
                                        "NULL": true
                                    }
                                }
                            },
                            "brand": {
                                "S": "visa"
                            }
                        }
                    },
                    "object": {
                        "S": "payment_method"
                    },
                    "customer": {
                        "NULL": true
                    }
                }
            },
            "active": {
                "BOOL": false
            },
            "savedAt": {
                "N": "1618890572124"
            },
            "ID": {
                "S": "8d22f1c6-1496-4a5b-9ad6-6bfd61313e9a"
            },
            "userId": {
                "S": "cb7650ca-214a-43df-a23d-27e8d7e585e0"
            },
            "brand": {
                "S": "visa"
            }
        },
        {
            "lastFour": {
                "S": "0101"
            },
            "valid": {
                "BOOL": false
            },
            "expMonth": {
                "N": "4"
            },
            "emailAddress": {
                "S": "stuheadz@gmail.com"
            },
            "expYear": {
                "N": "2034"
            },
            "paymentMethodId": {
                "S": "pm_1IiAZtKsNNk3qPPUXce6ybdI"
            },
            "paymentMethodObj": {
                "M": {
                    "billing_details": {
                        "M": {
                            "name": {
                                "NULL": true
                            },
                            "address": {
                                "M": {
                                    "country": {
                                        "NULL": true
                                    },
                                    "state": {
                                        "NULL": true
                                    },
                                    "postal_code": {
                                        "S": "43434"
                                    },
                                    "city": {
                                        "NULL": true
                                    },
                                    "line2": {
                                        "NULL": true
                                    },
                                    "line1": {
                                        "NULL": true
                                    }
                                }
                            },
                            "phone": {
                                "NULL": true
                            },
                            "email": {
                                "NULL": true
                            }
                        }
                    },
                    "livemode": {
                        "BOOL": false
                    },
                    "created": {
                        "N": "1618890525"
                    },
                    "id": {
                        "S": "pm_1IiAZtKsNNk3qPPUXce6ybdI"
                    },
                    "type": {
                        "S": "card"
                    },
                    "card": {
                        "M": {
                            "country": {
                                "S": "US"
                            },
                            "last4": {
                                "S": "0101"
                            },
                            "funding": {
                                "S": "credit"
                            },
                            "checks": {
                                "M": {
                                    "address_postal_code_check": {
                                        "NULL": true
                                    },
                                    "address_line1_check": {
                                        "NULL": true
                                    },
                                    "cvc_check": {
                                        "NULL": true
                                    }
                                }
                            },
                            "three_d_secure_usage": {
                                "M": {
                                    "supported": {
                                        "BOOL": true
                                    }
                                }
                            },
                            "wallet": {
                                "NULL": true
                            },
                            "generated_from": {
                                "NULL": true
                            },
                            "exp_month": {
                                "N": "4"
                            },
                            "exp_year": {
                                "N": "2034"
                            },
                            "networks": {
                                "M": {
                                    "available": {
                                        "L": [
                                            {
                                                "S": "visa"
                                            }
                                        ]
                                    },
                                    "preferred": {
                                        "NULL": true
                                    }
                                }
                            },
                            "brand": {
                                "S": "visa"
                            }
                        }
                    },
                    "object": {
                        "S": "payment_method"
                    },
                    "customer": {
                        "NULL": true
                    }
                }
            },
            "active": {
                "BOOL": false
            },
            "savedAt": {
                "N": "1618890453210"
            },
            "ID": {
                "S": "ffc9c946-49ae-4b9a-8491-6d70e66a2ff7"
            },
            "userId": {
                "S": "cb7650ca-214a-43df-a23d-27e8d7e585e0"
            },
            "brand": {
                "S": "visa"
            }
        },
        {
            "lastFour": {
                "S": "0002"
            },
            "valid": {
                "BOOL": false
            },
            "expMonth": {
                "N": "3"
            },
            "emailAddress": {
                "S": "stuheadz@gmail.com"
            },
            "expYear": {
                "N": "2042"
            },
            "paymentMethodId": {
                "S": "pm_1IiAZUKsNNk3qPPUBq7G3kN4"
            },
            "paymentMethodObj": {
                "M": {
                    "billing_details": {
                        "M": {
                            "name": {
                                "NULL": true
                            },
                            "address": {
                                "M": {
                                    "country": {
                                        "NULL": true
                                    },
                                    "state": {
                                        "NULL": true
                                    },
                                    "postal_code": {
                                        "S": "24342"
                                    },
                                    "city": {
                                        "NULL": true
                                    },
                                    "line2": {
                                        "NULL": true
                                    },
                                    "line1": {
                                        "NULL": true
                                    }
                                }
                            },
                            "phone": {
                                "NULL": true
                            },
                            "email": {
                                "NULL": true
                            }
                        }
                    },
                    "livemode": {
                        "BOOL": false
                    },
                    "created": {
                        "N": "1618890501"
                    },
                    "id": {
                        "S": "pm_1IiAZUKsNNk3qPPUBq7G3kN4"
                    },
                    "type": {
                        "S": "card"
                    },
                    "card": {
                        "M": {
                            "country": {
                                "S": "US"
                            },
                            "last4": {
                                "S": "0002"
                            },
                            "funding": {
                                "S": "credit"
                            },
                            "checks": {
                                "M": {
                                    "address_postal_code_check": {
                                        "NULL": true
                                    },
                                    "address_line1_check": {
                                        "NULL": true
                                    },
                                    "cvc_check": {
                                        "NULL": true
                                    }
                                }
                            },
                            "three_d_secure_usage": {
                                "M": {
                                    "supported": {
                                        "BOOL": true
                                    }
                                }
                            },
                            "wallet": {
                                "NULL": true
                            },
                            "generated_from": {
                                "NULL": true
                            },
                            "exp_month": {
                                "N": "3"
                            },
                            "exp_year": {
                                "N": "2042"
                            },
                            "networks": {
                                "M": {
                                    "available": {
                                        "L": [
                                            {
                                                "S": "visa"
                                            }
                                        ]
                                    },
                                    "preferred": {
                                        "NULL": true
                                    }
                                }
                            },
                            "brand": {
                                "S": "visa"
                            }
                        }
                    },
                    "object": {
                        "S": "payment_method"
                    },
                    "customer": {
                        "NULL": true
                    }
                }
            },
            "active": {
                "BOOL": false
            },
            "savedAt": {
                "N": "1618890428522"
            },
            "ID": {
                "S": "83078fb6-32c6-4848-be07-158e272a31f8"
            },
            "userId": {
                "S": "cb7650ca-214a-43df-a23d-27e8d7e585e0"
            },
            "brand": {
                "S": "visa"
            }
        },
        {
            "lastFour": {
                "S": "9979"
            },
            "valid": {
                "BOOL": false
            },
            "expMonth": {
                "N": "3"
            },
            "emailAddress": {
                "S": "stuheadz@gmail.com"
            },
            "expYear": {
                "N": "2034"
            },
            "paymentMethodId": {
                "S": "pm_1IiAcCKsNNk3qPPUTT4viNfC"
            },
            "paymentMethodObj": {
                "M": {
                    "billing_details": {
                        "M": {
                            "name": {
                                "NULL": true
                            },
                            "address": {
                                "M": {
                                    "country": {
                                        "NULL": true
                                    },
                                    "state": {
                                        "NULL": true
                                    },
                                    "postal_code": {
                                        "S": "34343"
                                    },
                                    "city": {
                                        "NULL": true
                                    },
                                    "line2": {
                                        "NULL": true
                                    },
                                    "line1": {
                                        "NULL": true
                                    }
                                }
                            },
                            "phone": {
                                "NULL": true
                            },
                            "email": {
                                "NULL": true
                            }
                        }
                    },
                    "livemode": {
                        "BOOL": false
                    },
                    "created": {
                        "N": "1618890668"
                    },
                    "id": {
                        "S": "pm_1IiAcCKsNNk3qPPUTT4viNfC"
                    },
                    "type": {
                        "S": "card"
                    },
                    "card": {
                        "M": {
                            "country": {
                                "S": "US"
                            },
                            "last4": {
                                "S": "9979"
                            },
                            "funding": {
                                "S": "credit"
                            },
                            "checks": {
                                "M": {
                                    "address_postal_code_check": {
                                        "NULL": true
                                    },
                                    "address_line1_check": {
                                        "NULL": true
                                    },
                                    "cvc_check": {
                                        "NULL": true
                                    }
                                }
                            },
                            "three_d_secure_usage": {
                                "M": {
                                    "supported": {
                                        "BOOL": true
                                    }
                                }
                            },
                            "wallet": {
                                "NULL": true
                            },
                            "generated_from": {
                                "NULL": true
                            },
                            "exp_month": {
                                "N": "3"
                            },
                            "exp_year": {
                                "N": "2034"
                            },
                            "networks": {
                                "M": {
                                    "available": {
                                        "L": [
                                            {
                                                "S": "visa"
                                            }
                                        ]
                                    },
                                    "preferred": {
                                        "NULL": true
                                    }
                                }
                            },
                            "brand": {
                                "S": "visa"
                            }
                        }
                    },
                    "object": {
                        "S": "payment_method"
                    },
                    "customer": {
                        "NULL": true
                    }
                }
            },
            "active": {
                "BOOL": false
            },
            "savedAt": {
                "N": "1618890595634"
            },
            "ID": {
                "S": "db767d0e-efe2-4420-ade9-4e4bfd75da0b"
            },
            "userId": {
                "S": "cb7650ca-214a-43df-a23d-27e8d7e585e0"
            },
            "brand": {
                "S": "visa"
            }
        },
        {
            "lastFour": {
                "S": "0119"
            },
            "valid": {
                "BOOL": false
            },
            "expMonth": {
                "N": "3"
            },
            "emailAddress": {
                "S": "stuheadz@gmail.com"
            },
            "expYear": {
                "N": "2023"
            },
            "paymentMethodId": {
                "S": "pm_1IiAdLKsNNk3qPPUUjfc7puS"
            },
            "paymentMethodObj": {
                "M": {
                    "billing_details": {
                        "M": {
                            "name": {
                                "NULL": true
                            },
                            "address": {
                                "M": {
                                    "country": {
                                        "NULL": true
                                    },
                                    "state": {
                                        "NULL": true
                                    },
                                    "postal_code": {
                                        "S": "32323"
                                    },
                                    "city": {
                                        "NULL": true
                                    },
                                    "line2": {
                                        "NULL": true
                                    },
                                    "line1": {
                                        "NULL": true
                                    }
                                }
                            },
                            "phone": {
                                "NULL": true
                            },
                            "email": {
                                "NULL": true
                            }
                        }
                    },
                    "livemode": {
                        "BOOL": false
                    },
                    "created": {
                        "N": "1618890739"
                    },
                    "id": {
                        "S": "pm_1IiAdLKsNNk3qPPUUjfc7puS"
                    },
                    "type": {
                        "S": "card"
                    },
                    "card": {
                        "M": {
                            "country": {
                                "S": "US"
                            },
                            "last4": {
                                "S": "0119"
                            },
                            "funding": {
                                "S": "credit"
                            },
                            "checks": {
                                "M": {
                                    "address_postal_code_check": {
                                        "NULL": true
                                    },
                                    "address_line1_check": {
                                        "NULL": true
                                    },
                                    "cvc_check": {
                                        "NULL": true
                                    }
                                }
                            },
                            "three_d_secure_usage": {
                                "M": {
                                    "supported": {
                                        "BOOL": true
                                    }
                                }
                            },
                            "wallet": {
                                "NULL": true
                            },
                            "generated_from": {
                                "NULL": true
                            },
                            "exp_month": {
                                "N": "3"
                            },
                            "exp_year": {
                                "N": "2023"
                            },
                            "networks": {
                                "M": {
                                    "available": {
                                        "L": [
                                            {
                                                "S": "visa"
                                            }
                                        ]
                                    },
                                    "preferred": {
                                        "NULL": true
                                    }
                                }
                            },
                            "brand": {
                                "S": "visa"
                            }
                        }
                    },
                    "object": {
                        "S": "payment_method"
                    },
                    "customer": {
                        "NULL": true
                    }
                }
            },
            "active": {
                "BOOL": false
            },
            "savedAt": {
                "N": "1618890666523"
            },
            "ID": {
                "S": "3328243f-50b7-4031-89e9-0f0be8129e42"
            },
            "userId": {
                "S": "cb7650ca-214a-43df-a23d-27e8d7e585e0"
            },
            "brand": {
                "S": "visa"
            }
        },
        {
            "lastFour": {
                "S": "0019"
            },
            "valid": {
                "BOOL": false
            },
            "expMonth": {
                "N": "2"
            },
            "emailAddress": {
                "S": "stuheadz@gmail.com"
            },
            "expYear": {
                "N": "2032"
            },
            "paymentMethodId": {
                "S": "pm_1IiAb6KsNNk3qPPUNZ97mq2d"
            },
            "paymentMethodObj": {
                "M": {
                    "billing_details": {
                        "M": {
                            "name": {
                                "NULL": true
                            },
                            "address": {
                                "M": {
                                    "country": {
                                        "NULL": true
                                    },
                                    "state": {
                                        "NULL": true
                                    },
                                    "postal_code": {
                                        "S": "23232"
                                    },
                                    "city": {
                                        "NULL": true
                                    },
                                    "line2": {
                                        "NULL": true
                                    },
                                    "line1": {
                                        "NULL": true
                                    }
                                }
                            },
                            "phone": {
                                "NULL": true
                            },
                            "email": {
                                "NULL": true
                            }
                        }
                    },
                    "livemode": {
                        "BOOL": false
                    },
                    "created": {
                        "N": "1618890600"
                    },
                    "id": {
                        "S": "pm_1IiAb6KsNNk3qPPUNZ97mq2d"
                    },
                    "type": {
                        "S": "card"
                    },
                    "card": {
                        "M": {
                            "country": {
                                "S": "US"
                            },
                            "last4": {
                                "S": "0019"
                            },
                            "funding": {
                                "S": "credit"
                            },
                            "checks": {
                                "M": {
                                    "address_postal_code_check": {
                                        "NULL": true
                                    },
                                    "address_line1_check": {
                                        "NULL": true
                                    },
                                    "cvc_check": {
                                        "NULL": true
                                    }
                                }
                            },
                            "three_d_secure_usage": {
                                "M": {
                                    "supported": {
                                        "BOOL": true
                                    }
                                }
                            },
                            "wallet": {
                                "NULL": true
                            },
                            "generated_from": {
                                "NULL": true
                            },
                            "exp_month": {
                                "N": "2"
                            },
                            "exp_year": {
                                "N": "2032"
                            },
                            "networks": {
                                "M": {
                                    "available": {
                                        "L": [
                                            {
                                                "S": "visa"
                                            }
                                        ]
                                    },
                                    "preferred": {
                                        "NULL": true
                                    }
                                }
                            },
                            "brand": {
                                "S": "visa"
                            }
                        }
                    },
                    "object": {
                        "S": "payment_method"
                    },
                    "customer": {
                        "NULL": true
                    }
                }
            },
            "active": {
                "BOOL": false
            },
            "savedAt": {
                "N": "1618890527625"
            },
            "ID": {
                "S": "0682060f-c10b-4e9c-bd52-f9ea5bafe505"
            },
            "userId": {
                "S": "cb7650ca-214a-43df-a23d-27e8d7e585e0"
            },
            "brand": {
                "S": "visa"
            }
        }
    ],
    "Count": 12,
    "ScannedCount": 12,
    "ConsumedCapacity": null
}
